{
    "CS201": "Data Structures and Algorithms",
    "CS202": "Operating Systems",
    "CS203": "Discrete Mathematics",
    "CS204": "Data Structures and Algorithms Laboratory",
    "CS205": "Operating Systems Lab",
    "MA204": "Probability, Statistics and Stochastic Processes",
    "CS251": "Object Oriented Programming",
    "CS252": "Design and Analysis of Algorithms",
    "EC237": "Digital Logic Design",
    "CS253": "Computer Organization and Architecture",
    "CS254": "Theory of Computation",
    "CS255": "Database Management Systems",
    "CS256": "Unix Tools and Shell Scripting Lab",
    "CS257": "Database Management Systems Lab"
}